fft_dev/__init__.py
fft_dev/version.py
fft_dev/fft3562a/__init__.py
fft_dev/fft3562a/fft3562a_dev_mock.py
fft_dev/fft3562a/fft3562a_dev_prologix.py
fft_dev/fft3562a/fft3562a_form.py
fft_dev/fft35670a/__init__.py
fft_dev/fft35670a/fft35670a_dev_prologix.py
fft_dev/fft35670a/fft35670a_form.py
fft_dev-0.4.6a1.data/scripts/fft3562a-cli
fft_dev-0.4.6a1.data/scripts/fft3562a-gui
fft_dev-0.4.6a1.data/scripts/fft35670a-gui
fft_dev-0.4.6a1.dist-info/LICENSE.txt
fft_dev-0.4.6a1.dist-info/METADATA
fft_dev-0.4.6a1.dist-info/WHEEL
fft_dev-0.4.6a1.dist-info/top_level.txt
fft_dev-0.4.6a1.dist-info/RECORD
