Metadata-Version: 2.1
Name: fft-dev
Version: 0.4.6a1
Summary: Driver and UI for HP 3562A and 35670A FFT analyzer
Home-page: https://gitlab.com/bendub/fft_dev
Author: Benoit Dubois
Author-email: benoit.dubois@femto-enginneering.fr
License: UNKNOWN
Platform: UNKNOWN
Classifier: Development Status :: 4 - Beta
Classifier: Environment :: Console
Classifier: Environment :: X11 Applications :: Qt
Classifier: Intended Audience :: End Users/Desktop
Classifier: License :: OSI Approved :: GNU Lesser General Public License v3 or later (LGPLv3+)
Classifier: Natural Language :: English
Classifier: Operating System :: POSIX :: Linux
Classifier: Programming Language :: Python
Classifier: Topic :: Scientific/Engineering
License-File: LICENSE.txt
Requires-Dist: PyQt5
Requires-Dist: numpy
Requires-Dist: pyqtgraph
Requires-Dist: iopy
